smartem_workspace/__init__.py
smartem_workspace/__main__.py
smartem_workspace/cli.py
smartem_workspace/commands/__init__.py
smartem_workspace/commands/check.py
smartem_workspace/commands/claude.py
smartem_workspace/commands/sync.py
smartem_workspace/config/__init__.py
smartem_workspace/config/claude-code-config.json
smartem_workspace/config/dev-requirements.json
smartem_workspace/config/loader.py
smartem_workspace/config/repos.json
smartem_workspace/config/schema.py
smartem_workspace/interactive/__init__.py
smartem_workspace/interactive/prompts.py
smartem_workspace/setup/__init__.py
smartem_workspace/setup/bootstrap.py
smartem_workspace/setup/claude.py
smartem_workspace/setup/repos.py
smartem_workspace/setup/serena.py
smartem_workspace/setup/workspace.py
smartem_workspace/utils/__init__.py
smartem_workspace/utils/git.py
smartem_workspace/utils/paths.py
smartem_workspace-0.5.0.dist-info/METADATA
smartem_workspace-0.5.0.dist-info/WHEEL
smartem_workspace-0.5.0.dist-info/entry_points.txt
smartem_workspace-0.5.0.dist-info/RECORD
