Metadata-Version: 2.4
Name: smartem-workspace
Version: 0.5.0
Summary: CLI tool to automate SmartEM multi-repo workspace setup
Project-URL: Homepage, https://github.com/DiamondLightSource/smartem-devtools
Project-URL: Documentation, https://diamondlightsource.github.io/smartem-devtools/
Project-URL: Repository, https://github.com/DiamondLightSource/smartem-devtools
Project-URL: Issues, https://github.com/DiamondLightSource/smartem-devtools/issues
Author-email: Diamond Light Source <smartem@diamond.ac.uk>
License-Expression: Apache-2.0
Keywords: cryo-em,development,smartem,workspace
Classifier: Development Status :: 3 - Alpha
Classifier: Environment :: Console
Classifier: Intended Audience :: Developers
Classifier: License :: OSI Approved :: Apache Software License
Classifier: Operating System :: OS Independent
Classifier: Programming Language :: Python :: 3
Classifier: Programming Language :: Python :: 3.11
Classifier: Programming Language :: Python :: 3.12
Classifier: Topic :: Software Development :: Build Tools
Requires-Python: >=3.11
Requires-Dist: httpx>=0.27.0
Requires-Dist: pydantic>=2.0.0
Requires-Dist: pyyaml>=6.0.0
Requires-Dist: rich>=13.0.0
Requires-Dist: typer>=0.12.0
Provides-Extra: dev
Requires-Dist: pytest-cov>=4.0.0; extra == 'dev'
Requires-Dist: pytest>=8.0.0; extra == 'dev'
Requires-Dist: ruff>=0.4.0; extra == 'dev'
